<Properties StartupConfiguration="{9F94E66D-0073-06B6-1765-F37AFFF31CA8}|">
  <MonoDevelop.Ide.ItemProperties.Assembly-CSharp PreferredExecutionTarget="Unity.Editor" />
  <MonoDevelop.Ide.Workbench ActiveDocument="Assets/Scripts/alan/IceDownForce.cs">
    <Files>
      <File FileName="Assets/Scripts/alan/Balance.cs" Line="40" Column="6" />
      <File FileName="Assets/Scripts/alan/IceMeltAndCreateWater.cs" Line="43" Column="18" />
      <File FileName="Assets/Scripts/alan/ReduceParentMass.cs" Line="26" Column="17" />
      <File FileName="Assets/Scripts/alan/RivetsFire.cs" Line="12" Column="29" />
      <File FileName="Assets/Scripts/alan/Force.cs" Line="13" Column="54" />
      <File FileName="Assets/Scripts/alan/AddDownForce.cs" Line="16" Column="1" />
      <File FileName="Assets/Scripts/alan/IceDownForce.cs" Line="14" Column="3" />
    </Files>
  </MonoDevelop.Ide.Workbench>
  <MonoDevelop.Ide.Workspace ActiveConfiguration="Debug" />
  <MonoDevelop.Ide.DebuggingService.Breakpoints>
    <BreakpointStore />
  </MonoDevelop.Ide.DebuggingService.Breakpoints>
  <MonoDevelop.Ide.DebuggingService.PinnedWatches />
  <MultiItemStartupConfigurations />
</Properties>